setux/mappings/packages.py
setux/mappings/services.py
setux_mappings-0.2343.0.dist-info/METADATA
setux_mappings-0.2343.0.dist-info/WHEEL
setux_mappings-0.2343.0.dist-info/top_level.txt
setux_mappings-0.2343.0.dist-info/RECORD
