Metadata-Version: 2.1
Name: setux-mappings
Version: 0.2343.0
Summary: System deployment
Home-page: https://notabug.org/dugres/setux_mappings
Author: Louis RIVIERE
Author-email: Louis RIVIERE <louis@riviere.xyz>
License: MIT
Project-URL: pypi, https://pypi.org/project/setux-managers
Project-URL: repository, https://bitbucket.org/dugres/setux_managers
Keywords: utility
Classifier: Development Status :: 3 - Alpha
Classifier: License :: OSI Approved :: MIT License
Classifier: Programming Language :: Python :: 3
Classifier: Operating System :: POSIX :: Linux
Classifier: Environment :: Console
Classifier: Intended Audience :: Developers
Classifier: Intended Audience :: Information Technology
Classifier: Intended Audience :: System Administrators
Classifier: Topic :: System :: Installation/Setup
Classifier: Topic :: System :: Systems Administration
Classifier: Topic :: Utilities
Requires-Python: >=3.9
Requires-Dist: setux-core >=0.2343.0
